fir_filter.v
module fir_filter (
    input wire clk,
    input wire rst,
    input wire signed [15:0] x_in,
    output reg signed [15:0] y_out
);

    reg signed [15:0] x_delay;

    // Q15 coefficients
    localparam signed [15:0] A = 16'sd16384; // 0.5
    localparam signed [15:0] B = 16'sd16384; // 0.5

    reg signed [31:0] mult_a;
    reg signed [31:0] mult_b;
    reg signed [31:0] sum;

    always @(posedge clk) begin
        if (rst) begin
            x_delay <= 0;
            y_out   <= 0;
        end else begin
            mult_a <= A * x_in;
            mult_b <= B * x_delay;
            sum    <= mult_a + mult_b;
            y_out  <= sum >>> 15; // scale back
            x_delay <= x_in;
        end
    end

endmodule

fir_tb.v
`timescale 1ns/1ps

module fir_tb;

    reg clk;
    reg rst;
    reg signed [15:0] x_in;
    wire signed [15:0] y_out;

    // Instantiate FIR filter
    fir_filter dut (
        .clk(clk),
        .rst(rst),
        .x_in(x_in),
        .y_out(y_out)
    );

    // Clock generation (10 ns period)
    always #5 clk = ~clk;

    initial begin
        // Initialize
        clk = 0;
        rst = 1;
        x_in = 0;

        // Waveform dump
        $dumpfile("fir_wave.vcd");
        $dumpvars(0, fir_tb);

        // Release reset
        #20 rst = 0;

        // Apply input samples
        #10 x_in = 16'sd10;
        #10 x_in = 16'sd20;
        #10 x_in = 16'sd30;
        #10 x_in = 16'sd40;
        #10 x_in = 16'sd50;

        #50 $finish;
    end

endmodule

fir_wave.vcd
$date
	Tue Dec 30 23:10:47 2025
$end
$version
	Icarus Verilog
$end
$timescale
	1ps
$end
$scope module fir_tb $end
$var wire 16 ! y_out [15:0] $end
$var reg 1 " clk $end
$var reg 1 # rst $end
$var reg 16 $ x_in [15:0] $end
$scope module dut $end
$var wire 1 " clk $end
$var wire 1 # rst $end
$var wire 16 % x_in [15:0] $end
$var parameter 16 & A $end
$var parameter 16 ' B $end
$var reg 32 ( mult_a [31:0] $end
$var reg 32 ) mult_b [31:0] $end
$var reg 32 * sum [31:0] $end
$var reg 16 + x_delay [15:0] $end
$var reg 16 , y_out [15:0] $end
$upscope $end
$upscope $end
$enddefinitions $end
$comment Show the parameter values. $end
$dumpall
b100000000000000 '
b100000000000000 &
$end
#0
$dumpvars
bx ,
bx +
bx *
bx )
bx (
b0 %
b0 $
1#
0"
bx !
$end
#5000
b0 !
b0 ,
b0 +
1"
#10000
0"
#15000
1"
#20000
0"
0#
#25000
bx !
bx ,
b0 )
b0 (
1"
#30000
0"
b1010 $
b1010 %
#35000
b1010 +
b0 *
b101000000000000000 (
1"
#40000
0"
b10100 $
b10100 %
#45000
b10100 +
b0 !
b0 ,
b101000000000000000 *
b101000000000000000 )
b1010000000000000000 (
1"
#50000
0"
b11110 $
b11110 %
#55000
b11110 +
b101 !
b101 ,
b1111000000000000000 *
b1010000000000000000 )
b1111000000000000000 (
1"
#60000
0"
b101000 $
b101000 %
#65000
b101000 +
b1111 !
b1111 ,
b11001000000000000000 *
b1111000000000000000 )
b10100000000000000000 (
1"
#70000
0"
b110010 $
b110010 %
#75000
b110010 +
b11001 !
b11001 ,
b100011000000000000000 *
b10100000000000000000 )
b11001000000000000000 (
1"
#80000
0"
#85000
b100011 !
b100011 ,
b101101000000000000000 *
b11001000000000000000 )
1"
#90000
0"
#95000
b101101 !
b101101 ,
b110010000000000000000 *
1"
#100000
0"
#105000
b110010 !
b110010 ,
1"
